ripley/__init__.py
ripley/_clickhouse/__init__.py
ripley/_clickhouse/clickhouse_base_service.py
ripley/_clickhouse/clickhouse_cmd.py
ripley/_clickhouse/clickhouse_partition_cmd.py
ripley/_clickhouse/clickhouse_partition_service.py
ripley/_clickhouse/clickhouse_proxy.py
ripley/_clickhouse/clickhouse_system_service.py
ripley/_clickhouse/clickhouse_table_service.py
ripley/_clickhouse_protocols.py
ripley/_sql_cmd/__init__.py
ripley/_sql_cmd/base_sql_cmd.py
ripley/models/__init__.py
ripley/models/base_model.py
ripley/models/clickhouse_db.py
ripley/models/clickhouse_disk.py
ripley/models/clickhouse_global_counter.py
ripley/models/clickhouse_partition.py
ripley/models/clickhouse_process.py
ripley/models/clickhouse_table.py
ripley-0.dev133.dist-info/LICENSE
ripley-0.dev133.dist-info/WHEEL
ripley-0.dev133.dist-info/METADATA
ripley-0.dev133.dist-info/RECORD
