Metadata-Version: 2.1
Name: ripley
Version: 0.dev133
Summary: data / database manipulation tool. See: https://gitlab.com/d-ganchar/ripley/-/pipelines/1498198176/
License: MIT
Keywords: data,database,sql,clickhouse
Author: Danila Ganchar
Requires-Python: >=3.8,<3.13
Classifier: Development Status :: 3 - Alpha
Classifier: License :: OSI Approved :: MIT License
Classifier: Programming Language :: Python :: 3
Classifier: Programming Language :: Python :: 3.8
Classifier: Programming Language :: Python :: 3.9
Classifier: Programming Language :: Python :: 3.10
Classifier: Programming Language :: Python :: 3.10
Classifier: Programming Language :: Python :: 3.11
Classifier: Programming Language :: Python :: 3.12
Classifier: Programming Language :: Python :: 3.8
Classifier: Programming Language :: Python :: 3.9
Classifier: Programming Language :: SQL
Classifier: Topic :: Database
